cic_utils/__init__.py
cic_utils/converters.py
cic_utils-0.2.5.dist-info/LICENSE
cic_utils-0.2.5.dist-info/WHEEL
cic_utils-0.2.5.dist-info/METADATA
cic_utils-0.2.5.dist-info/RECORD
