Metadata-Version: 2.1
Name: cic-utils
Version: 0.2.5
Summary: 
Home-page: https://git.grassecon.net/grassrootseconomics/cic-utils
License: GPL-3.0-or-later
Author: William Luke
Author-email: williamluke4@gmail.com
Requires-Python: >=3.7,<4.0
Classifier: License :: OSI Approved :: GNU General Public License v3 or later (GPLv3+)
Classifier: Programming Language :: Python :: 3
Classifier: Programming Language :: Python :: 3.10
Classifier: Programming Language :: Python :: 3.7
Classifier: Programming Language :: Python :: 3.8
Classifier: Programming Language :: Python :: 3.9
Project-URL: Repository, https://git.grassecon.net/grassrootseconomics/cic-utils
